my_latex_package/__init__.py
my_latex_package-0.2.dist-info/METADATA
my_latex_package-0.2.dist-info/WHEEL
my_latex_package-0.2.dist-info/top_level.txt
my_latex_package-0.2.dist-info/RECORD
